miller_rabin_cyriac_benousaad/__init__.py
miller_rabin_cyriac_benousaad/verification.py
miller_rabin_cyriac_benousaad-1.2.3.dist-info/LICENSE.md
miller_rabin_cyriac_benousaad-1.2.3.dist-info/METADATA
miller_rabin_cyriac_benousaad-1.2.3.dist-info/WHEEL
miller_rabin_cyriac_benousaad-1.2.3.dist-info/RECORD
